data_auto_profiler/__init__.py
data_auto_profiler/core.py
data_auto_profiler-0.1.1.dist-info/LICENSE
data_auto_profiler-0.1.1.dist-info/METADATA
data_auto_profiler-0.1.1.dist-info/WHEEL
data_auto_profiler-0.1.1.dist-info/top_level.txt
data_auto_profiler-0.1.1.dist-info/RECORD
