Metadata-Version: 2.1
Name: data-auto-profiler
Version: 0.1.1
Summary: Automated data profiling and visualization tool
Home-page: https://github.com/CharlesMaponya/autoprofile
Author: Charles Maponya
Author-email: maponyacl@gmail.com
Classifier: Programming Language :: Python :: 3
Classifier: License :: OSI Approved :: MIT License
Classifier: Operating System :: OS Independent
Requires-Python: >=3.8
License-File: LICENSE
Requires-Dist: pandas>=2.2.2
Requires-Dist: numpy>=1.26.4
Requires-Dist: plotly>=5.22.0
Requires-Dist: scipy>=1.13.1
Requires-Dist: nbformat>=4.2.0
